{"name":"Menufor8","tagline":"Windows 8を対象としたスタートメニュークローンです。Windows 7のスタートメニューを可能な限り再現する事を目標としています。Windows 8.1以上は対象としていません。","body":"# Menu For 8について\r\n\r\n## はじめに\r\nMenu For 8のソースコードです。  \r\nこれはWindows 8向けのスタートメニュークローン・ランチャーです。  \r\nWindows 8.1でスタートボタンが復活したため、**このソフトは現在適切に動作しません。**私も使ってません。\r\n\r\nWindowsAPICodePack関係のファイルを除いてあります。  \r\n実際にコンパイルするには、以下のサイトからWindows(R) API Code Pack for Microsoft(R) .NET Framework ver 1.1をダウンロード、展開し、参照を追加しなおしてください。  \r\nhttp://archive.msdn.microsoft.com/WindowsAPICodePack  \r\nsetup.zipには含むため、一部別のライセンスが適用されます。\r\n\r\nまたlogo内には、ロゴのicoファイルとPaint.net用の画像ファイルがあります。  \r\nico4.pdnはレイヤー等の情報が含まれています。  \r\n商標等に細心の注意を払い利用してください。  \r\n\r\n## 注意\r\n* リソース(Properties/Resources.resx)からコード(Properties/Resources.Designer.cs)を自動作成するResGen.exeに問題があり、コンストラクタ(Properties/Resources.Designer.cs内Resources())をinternalで作成するようです。この時、場合によって正常にコンパイルできなくなります。  \r\n本来はアクセッサークラスを作成すべきですが、暫定的に``internal Resources() {``\r\nをこのように``public Resources() {``\r\n書き換えています。  \r\nProperties/Resourcesのコンストラクタが見当たらないとの例外が発生した場合には(Mainwindow.xamlで発生します)同様に書き換えてみてください。  \r\n  参考:http://connect.microsoft.com/VisualStudio/feedback/details/628281/silverlight-wp7-resource-files-and-binding\r\n* 当初から名前を変更したため、名称に関して若干の混乱が発生しています。このソフトの名前はMenu For 8です。これは名称内にMicrosoft製品の名前を含まない・誤解を与えない事を目的とするものです。しかし、名前空間やクラス名などではStartMenuForWin8が使われています。あくまで開発中の名前で現在のソフトウェアの名前ではありません。ご注意ください。\r\n\r\n## 対象環境\r\n* Microsoft Visual Studio 2010シリーズまたはVisual C# 2010 Express。\r\n* 実行はWindows 8上を想定しています。Windows 7より前のOSでは正常に動作しない可能性もあります。\r\n* Windows 8.1以降ではスタートボタンが復活したため動作しません。\r\n\r\n## 連絡\r\n以下のメールアドレスにどうぞ。  \r\nkurema_makoto_software@yahoo.co.jp\r\n\r\n## アンインストール\r\n通常通り「プログラムのアンインストール」等の項目から削除できます。\r\n\r\n---------------------------------------------\r\n商標等について。\r\nMicrosoft は米国 Microsoft Corporation の米国およびその他の国における登録商標または商標です。  \r\nWindows、Windows Server、Windows Vista、Windows 7 は米国 Microsoft Corporation の米国およびその他の国における登録商標または商標です。  \r\nVisual Studio、Visual Basic、Visual C#、Visual C++ は米国 Microsoft Corporation の米国およびその他の国における登録商標または商標です。  \r\n.NET Framework は米国 Microsoft Corporation の米国およびその他の国における登録商標または商標です。  \r\nWindowsの正式名称は、Microsoft Windows Operating Systemです。  \r\nWindows 8は現時点での開発コードネームです。将来名称が変更される可能性があります。  \r\nその他、本ソフトウェアに記載の製品名は、各社の商標または登録商標です。  \r\n","google":"","note":"Don't delete this file! It's used internally to help with page regeneration."}